pyppl_report/__init__.py
pyppl_report/filters/__init__.py
pyppl_report/filters/image.py
pyppl_report/filters/link.py
pyppl_report/filters/table.py
pyppl_report/filters/utils.py
pyppl_report/report.py
pyppl_report/templates/bootstrap/static/adapter.js
pyppl_report/templates/bootstrap/static/bootstrap.min.css
pyppl_report/templates/bootstrap/static/bootstrap.min.js
pyppl_report/templates/bootstrap/static/datatables.min.css
pyppl_report/templates/bootstrap/static/datatables.min.js
pyppl_report/templates/bootstrap/static/echo.min.js
pyppl_report/templates/bootstrap/static/jquery.min.js
pyppl_report/templates/bootstrap/static/template.css
pyppl_report/templates/bootstrap/static/template.js
pyppl_report/templates/bootstrap/template.html
pyppl_report/templates/layui/.gitignore
pyppl_report/templates/layui/static/adapter.js
pyppl_report/templates/layui/static/css/layui.css
pyppl_report/templates/layui/static/css/layui.mobile.css
pyppl_report/templates/layui/static/css/modules/code.css
pyppl_report/templates/layui/static/css/modules/laydate/default/font.css
pyppl_report/templates/layui/static/css/modules/laydate/default/laydate.css
pyppl_report/templates/layui/static/css/modules/layer/default/icon-ext.png
pyppl_report/templates/layui/static/css/modules/layer/default/icon.png
pyppl_report/templates/layui/static/css/modules/layer/default/layer.css
pyppl_report/templates/layui/static/css/modules/layer/default/loading-0.gif
pyppl_report/templates/layui/static/css/modules/layer/default/loading-1.gif
pyppl_report/templates/layui/static/css/modules/layer/default/loading-2.gif
pyppl_report/templates/layui/static/font/iconfont.eot
pyppl_report/templates/layui/static/font/iconfont.svg
pyppl_report/templates/layui/static/font/iconfont.ttf
pyppl_report/templates/layui/static/font/iconfont.woff
pyppl_report/templates/layui/static/font/iconfont.woff2
pyppl_report/templates/layui/static/image-preview.jpg
pyppl_report/templates/layui/static/images/face/0.gif
pyppl_report-0.6.2.dist-info/entry_points.txt
pyppl_report-0.6.2.dist-info/WHEEL
pyppl_report-0.6.2.dist-info/METADATA
pyppl_report-0.6.2.dist-info/RECORD
