Metadata-Version: 2.1
Name: pyppl-report
Version: 0.6.2
Summary: A report generating system for PyPPL
Home-page: https://github.com/pwwang/pyppl_report
License: MIT
Author: pwwang
Author-email: pwwang@pwwang.com
Requires-Python: >=3.6,<4.0
Classifier: License :: OSI Approved :: MIT License
Classifier: Programming Language :: Python :: 3
Classifier: Programming Language :: Python :: 3.6
Classifier: Programming Language :: Python :: 3.7
Classifier: Programming Language :: Python :: 3.8
Requires-Dist: cmdy
Requires-Dist: liquidpy
Requires-Dist: panflute (>=1.11.0,<1.12.0)
Requires-Dist: pyppl
Requires-Dist: toml (>=0.10,<0.11)
Project-URL: Repository, https://github.com/pwwang/pyppl_report
